pydeck_overlays/__init__.py
pydeck_overlays/labels.py
pydeck_overlays-0.1.2.dist-info/AUTHORS.rst
pydeck_overlays-0.1.2.dist-info/LICENSE
pydeck_overlays-0.1.2.dist-info/METADATA
pydeck_overlays-0.1.2.dist-info/WHEEL
pydeck_overlays-0.1.2.dist-info/top_level.txt
pydeck_overlays-0.1.2.dist-info/RECORD
