Metadata-Version: 2.1
Name: pydeck-overlays
Version: 0.1.2
Summary: Pydeck layers for map overlays
Home-page: https://github.com/oceanum-io/pydeck_overlays
Author: Oceanum Developers
Author-email: developers@oceanum.science
License: MIT license
Keywords: pydeck
Classifier: Development Status :: 2 - Pre-Alpha
Classifier: Intended Audience :: Developers
Classifier: License :: OSI Approved :: MIT License
Classifier: Natural Language :: English
Classifier: Programming Language :: Python :: 3
Classifier: Programming Language :: Python :: 3.6
Classifier: Programming Language :: Python :: 3.7
Classifier: Programming Language :: Python :: 3.8
License-File: LICENSE
License-File: AUTHORS.rst
Requires-Dist: pydeck
Requires-Dist: webcolors
